{"cameraMode":{"drawMode":0,"name":"Shaded","section":"Shading Mode"},"sceneLighting":true,"audioPlay":false,"sceneViewState":{"m_AlwaysRefresh":false,"showFog":true,"showSkybox":true,"showFlares":true,"showImageEffects":true,"showParticleSystems":true,"showVisualEffectGraphs":true,"m_FxEnabled":true},"in2DMode":false,"pivot":{"x":-179.2841339111328,"y":-25.267133712768556,"z":89.49059295654297},"rotation":{"x":0.32616710662841799,"y":-0.4687817394733429,"z":0.19154092669487,"w":0.7982491850852966},"size":220.6141815185547,"orthographic":false}